README
setup.py
jsend/__init__.py
jsend/jsend.py
jsend/test_jsend.py
jsend/test_jsend_pytest.py
python_jsend.egg-info/PKG-INFO
python_jsend.egg-info/SOURCES.txt
python_jsend.egg-info/dependency_links.txt
python_jsend.egg-info/top_level.txt