Metadata-Version: 1.1
Name: python-jsend
Version: 0.5.1
Summary: A python module for jsend
Home-page: https://github.com/darkdarkfruit/jsend
Author: darkdarkfruit
Author-email: darkdarkfruit@{nospam}gmail.com
License: MIT
Platform: any
Classifier: Development Status :: 4 - Beta
Classifier: Intended Audience :: Developers
Classifier: License :: OSI Approved :: MIT License
Classifier: Operating System :: OS Independent
Classifier: Programming Language :: Python
Classifier: Topic :: Internet
Classifier: Topic :: Software Development :: Libraries :: Python Modules
